pyterraformer/__init__.py
pyterraformer/config.py
pyterraformer/constants.py
pyterraformer/enums.py
pyterraformer/exceptions.py
pyterraformer/inventory.py
pyterraformer/py.typed
pyterraformer/settings.py
pyterraformer/core/__init__.py
pyterraformer/core/modules.py
pyterraformer/core/namespace.py
pyterraformer/core/objects.py
pyterraformer/core/syntax.py
pyterraformer/core/utility.py
pyterraformer/core/workspace.py
pyterraformer/core/generics/__init__.py
pyterraformer/core/generics/backend.py
pyterraformer/core/generics/comment.py
pyterraformer/core/generics/data.py
pyterraformer/core/generics/interpolation.py
pyterraformer/core/generics/literal.py
pyterraformer/core/generics/local.py
pyterraformer/core/generics/meta_arguments.py
pyterraformer/core/generics/metadata.py
pyterraformer/core/generics/output.py
pyterraformer/core/generics/terraform.py
pyterraformer/core/generics/terraform_block.py
pyterraformer/core/generics/variables.py
pyterraformer/core/resources/__init__.py
pyterraformer/core/resources/resource_object.py
pyterraformer/core/resources/unknown_resource.py
pyterraformer/providers/__init__.py
pyterraformer/serializer/__init__.py
pyterraformer/serializer/base_serializer.py
pyterraformer/serializer/human_serializer.py
pyterraformer/serializer/json_serializer.py
pyterraformer/serializer/load_templates.py
pyterraformer/serializer/human_resources/__init__.py
pyterraformer/serializer/human_resources/engine.py
pyterraformer/serializer/human_resources/module.py
pyterraformer/serializer/templates/__init__.py
pyterraformer/terraform/__init__.py
pyterraformer/terraform/settings.py
pyterraformer/terraform/terraform.py
pyterraformer/terraform/backends/__init__.py
pyterraformer/terraform/backends/artifactory_backend.py
pyterraformer/terraform/backends/azurerm_backend.py
pyterraformer/terraform/backends/base_backend.py
pyterraformer/terraform/backends/consul_backend.py
pyterraformer/terraform/backends/cos_backend.py
pyterraformer/terraform/backends/etcd_backend.py
pyterraformer-0.1.0.dist-info/licenses/LICENSE
pyterraformer-0.1.0.dist-info/METADATA
pyterraformer-0.1.0.dist-info/WHEEL
pyterraformer-0.1.0.dist-info/top_level.txt
pyterraformer-0.1.0.dist-info/RECORD
